yadd/__init__.py
yadd/__main__.py
yadd/__version__.py
yadd/py.typed
yadd/yadd_cli.py
yadd/yadd_module.py
yadd-0.3.0.dist-info/METADATA
yadd-0.3.0.dist-info/WHEEL
yadd-0.3.0.dist-info/licenses/LICENSE
yadd-0.3.0.dist-info/RECORD
