Metadata-Version: 2.3
Name: yadd
Version: 0.3.0
Summary: Yet Another dict Differ
Project-URL: Homepage, https://github.com/jamesabel/yadd
Project-URL: Source, https://github.com/jamesabel/yadd
Project-URL: Documentation, https://github.com/jamesabel/yadd
Author-email: James Abel <j@abel.co>
License: MIT License
License-File: LICENSE
Keywords: dict,differ
Requires-Python: >=3.10
Requires-Dist: ismain
Requires-Dist: tomli
